alembic_sdk/__init__.py
alembic_sdk/config.py
alembic_sdk/env_template.py
alembic_sdk/upgrade_head.py
alembic_sdk-0.1.7.dist-info/LICENSE
alembic_sdk-0.1.7.dist-info/METADATA
alembic_sdk-0.1.7.dist-info/WHEEL
alembic_sdk-0.1.7.dist-info/RECORD
