Metadata-Version: 2.1
Name: alembic-sdk
Version: 0.1.7
Summary: 
Author: Filipe Marchesini
Author-email: filipe.marchesini@gmail.com
Requires-Python: >=3.11,<4.0
Classifier: Programming Language :: Python :: 3
Classifier: Programming Language :: Python :: 3.11
Classifier: Programming Language :: Python :: 3.12
Requires-Dist: alembic (>=1.13.1,<2.0.0)
Requires-Dist: sqlmodel (>=0.0.14,<0.0.15)
Project-URL: Homepage, https://github.com/FilipeMarch/alembic-sdk
